{
  "post1": {
    "image": "img/posts/math/post1.jpg",
    "title": "Учим основные геометрические фигуры",
    "content": "Данная презентация подойдет для знакомства учащихся с основными геометрическими фигурами на уроках математики во 2-м и 3-м классах. Также ее можно использовать родителям при самостоятельном знакомстве детей с миром геометрии. В презентации вы найдете красочные слайды с изображением и описанием фигур. Материал можно использовать не только на онлайн-уроках, а также в качестве дополнительного материала для показа в классе. После загрузки презентации ее нужно открыть и запустить клавишей F5.",
    "link": "https://drive.google.com/file/d/1lhhYyP8BSLkbfMcHP6rmWiCAV9FMsEDx/view?usp=sharing",
    "prevImage": "img/preview/math/post1.jpg",
    "prevTitle": "Учим фигуры"
  }
}
